{
    "dataList":[
        {   
            "msgCode":101,
            "msgType":"认证服务订单通知",
            "templateDetails":"恭喜刘强230281198901021101通过1段定级考评，请于2019年6月1日前，前往公众号报名系统_我的订单缴纳认证服务费完成段级位认证，更多内容请咨询公众号“中国围棋协会”客服，关键字”认证服务“【智能考场】。",
            "editTime":"2019-2-25 19:20"
        },
        {   
            "msgCode":102,
            "msgType":"认证服务通知",
            "templateDetails":"恭喜刘强230281198901021101成功定级1段【智能考场】。",
            "editTime":"2019-2-25 19:20"
        },
        {
            "msgCode":103,
            "msgType":"考试结果通知",
            "templateDetails":"恭喜刘强23刘强230281198901021101本次1段定级考试中，取得90分【智能考场】。0281198901021101通过1段定级考评，请于2019年6月1日前，前往公众号报名系统_我的订单缴纳认证服务费完成段级位认证，更多内容请咨询公众号“中国围棋协会”客服，关键字”认证服务“【智能考场】。",
            "editTime":"2019-2-25 19:20"
        }
    ]
}